<?xml version="1.0" encoding="utf-8"?>
<!DOCTYPE hibernate-mapping PUBLIC "-//Hibernate/Hibernate Mapping DTD 3.0//EN"
"http://hibernate.sourceforge.net/hibernate-mapping-3.0.dtd">
<!-- 
    Mapping file autogenerated by MyEclipse Persistence Tools
-->
<hibernate-mapping>
    <class name="com.pkg.hibernate.TeacherToSubject" table="teacher_to_subject" catalog="maa">
        <composite-id name="id" class="com.pkg.hibernate.TeacherToSubjectId">
            <key-property name="personId" type="java.lang.String">
                <column name="Person_ID" length="15" />
            </key-property>
            <key-property name="subjectId" type="java.lang.String">
                <column name="Subject_Id" length="5" />
            </key-property>
        </composite-id>
        <version name="version" type="java.lang.Integer">
            <column name="Version" />
        </version>
        <many-to-one name="subject" class="com.pkg.hibernate.Subject" update="false" insert="false" fetch="select">
            <column name="Subject_Id" length="5" not-null="true" />
        </many-to-one>
        <property name="startDate" type="java.sql.Timestamp">
            <column name="Start_Date" length="19" />
        </property>
        <property name="endDate" type="java.sql.Timestamp">
            <column name="End_Date" length="19" />
        </property>
        <property name="description" type="java.lang.String">
            <column name="description" length="20" />
        </property>
        <set name="timeTables" inverse="true">
            <key>
                <column name="Subject_Id" length="5" />
                <column name="person_id" length="5" />
            </key>
            <one-to-many class="com.pkg.hibernate.TimeTable" />
        </set>
    </class>
</hibernate-mapping>
